{
    "data": [
        [
            0.7953125,
            0.825,
            0.011979166666666652,
            -0.04166666666666663,
            -0.05729166666666663,
            0.02129629629629637,
            0.03749999999999998,
            0.017592592592592604
        ],
        [
            0.7932291666666667,
            0.8175925925925925,
            0.006249999999999978,
            -0.05092592592592582,
            -0.055208333333333304,
            0.025000000000000022,
            0.038541666666666696,
            0.017592592592592604
        ],
        [
            0.7921875,
            0.8055555555555556,
            0.014062499999999978,
            -0.031481481481481555,
            -0.05104166666666676,
            0.0444444444444444,
            0.04166666666666663,
            0.03518518518518521
        ]
    ],
    "original_data": [
        {
            "time_step": 1,
            "original_data_path": "/content/drive/Othercomputers/\ub0b4 \ub178\ud2b8\ubd81/Forked_Models/Validation/Validation/_\ub77c\ubca8_General_val_C/district/3. \ud6c4\ubc29 \ubc29\ud5a5 \uc774\ubbf8\uc9c0/[district]leave_075C/[district]leave_075C_72.json",
            "id": 4
        },
        {
            "time_step": 2,
            "original_data_path": "/content/drive/Othercomputers/\ub0b4 \ub178\ud2b8\ubd81/Forked_Models/Validation/Validation/_\ub77c\ubca8_General_val_C/district/3. \ud6c4\ubc29 \ubc29\ud5a5 \uc774\ubbf8\uc9c0/[district]leave_075C/[district]leave_075C_74.json",
            "id": 4
        },
        {
            "time_step": 3,
            "original_data_path": "/content/drive/Othercomputers/\ub0b4 \ub178\ud2b8\ubd81/Forked_Models/Validation/Validation/_\ub77c\ubca8_General_val_C/district/3. \ud6c4\ubc29 \ubc29\ud5a5 \uc774\ubbf8\uc9c0/[district]leave_075C/[district]leave_075C_76.json",
            "id": 4
        }
    ],
    "label": 2
}