{
    "data": [
        [
            0.7963541666666667,
            0.8203703703703704,
            0.016666666666666607,
            -0.037962962962962976,
            -0.055208333333333415,
            0.02499999999999991,
            0.038541666666666585,
            -0.0037037037037037646
        ],
        [
            0.8005208333333333,
            0.8287037037037037,
            0.008854166666666607,
            -0.03981481481481486,
            -0.0630208333333333,
            0.017592592592592604,
            0.03802083333333328,
            -0.007407407407407418
        ],
        [
            0.790625,
            0.8157407407407408,
            0.012499999999999956,
            -0.037962962962962976,
            -0.05156250000000007,
            0.025000000000000022,
            0.04010416666666661,
            -0.0009259259259259967
        ]
    ],
    "original_data": [
        {
            "time_step": 1,
            "original_data_path": "/content/drive/Othercomputers/\ub0b4 \ub178\ud2b8\ubd81/Forked_Models/Validation/Validation/_\ub77c\ubca8_General_val_C/district/3. \ud6c4\ubc29 \ubc29\ud5a5 \uc774\ubbf8\uc9c0/[district]leave_075C/[district]leave_075C_28.json",
            "id": 4
        },
        {
            "time_step": 2,
            "original_data_path": "/content/drive/Othercomputers/\ub0b4 \ub178\ud2b8\ubd81/Forked_Models/Validation/Validation/_\ub77c\ubca8_General_val_C/district/3. \ud6c4\ubc29 \ubc29\ud5a5 \uc774\ubbf8\uc9c0/[district]leave_075C/[district]leave_075C_30.json",
            "id": 4
        },
        {
            "time_step": 3,
            "original_data_path": "/content/drive/Othercomputers/\ub0b4 \ub178\ud2b8\ubd81/Forked_Models/Validation/Validation/_\ub77c\ubca8_General_val_C/district/3. \ud6c4\ubc29 \ubc29\ud5a5 \uc774\ubbf8\uc9c0/[district]leave_075C/[district]leave_075C_32.json",
            "id": 4
        }
    ],
    "label": 2
}