{
    "data": [
        [
            0.5348958333333333,
            0.34629629629629627,
            0.008854166666666607,
            -0.08425925925925926,
            0.061979166666666696,
            0.09537037037037038,
            -0.07864583333333336,
            0.046296296296296335
        ],
        [
            0.5239583333333333,
            0.3333333333333333,
            0.002083333333333326,
            -0.09074074074074073,
            0.06510416666666674,
            0.08981481481481485,
            -0.07552083333333331,
            0.05462962962962964
        ],
        [
            0.5239583333333333,
            0.3333333333333333,
            0.004166666666666652,
            -0.08148148148148149,
            0.06510416666666674,
            0.08981481481481485,
            -0.07812499999999994,
            0.06481481481481483
        ]
    ],
    "original_data": [
        {
            "time_step": 1,
            "original_data_path": "/content/drive/Othercomputers/\ub0b4 \ub178\ud2b8\ubd81/Forked_Models/Validation/Validation/_\ub77c\ubca8_General_val_C/district_sample2/[district]night_989C/[district]night_989C_80.json",
            "id": 0
        },
        {
            "time_step": 2,
            "original_data_path": "/content/drive/Othercomputers/\ub0b4 \ub178\ud2b8\ubd81/Forked_Models/Validation/Validation/_\ub77c\ubca8_General_val_C/district_sample2/[district]night_989C/[district]night_989C_82.json",
            "id": 0
        },
        {
            "time_step": 3,
            "original_data_path": "/content/drive/Othercomputers/\ub0b4 \ub178\ud2b8\ubd81/Forked_Models/Validation/Validation/_\ub77c\ubca8_General_val_C/district_sample2/[district]night_989C/[district]night_989C_84.json",
            "id": 0
        }
    ],
    "label": 1
}